aomaker/__init__.py
aomaker/_aomaker.py
aomaker/_constants.py
aomaker/_log.py
aomaker/_printer.py
aomaker/aomaker.py
aomaker/cli.py
aomaker/config_handlers.py
aomaker/exceptions.py
aomaker/hook_manager.py
aomaker/log.py
aomaker/models.py
aomaker/param_types.py
aomaker/path.py
aomaker/pytest_plugins.py
aomaker/report.py
aomaker/scaffold.py
aomaker/service.py
aomaker/session.py
aomaker/storage.py
aomaker/base/__init__.py
aomaker/base/base_testcase.py
aomaker/core/__init__.py
aomaker/core/api_object.py
aomaker/core/apischema_attrs.py
aomaker/core/base_model.py
aomaker/core/converters.py
aomaker/core/http_client.py
aomaker/core/request_builder.py
aomaker/core/router.py
aomaker/core/middlewares/__init__.py
aomaker/core/middlewares/logging_middleware.py
aomaker/core/middlewares/registry.py
aomaker/database/__init__.py
aomaker/database/mysql.py
aomaker/database/sqlite.py
aomaker/extension/__init__.py
aomaker/extension/retry/__init__.py
aomaker/extension/retry/retry.py
aomaker/html/progress.html
aomaker/html/template.html
aomaker/maker/__init__.py
aomaker/maker/cli_handlers.py
aomaker/maker/compat.py
aomaker/maker/config.py
aomaker/maker/generator.py
aomaker/maker/jsonschema.py
aomaker/maker/models.py
aomaker/maker/parser.py
aomaker/maker/utils.py
aomaker/maker/templates/__init__.py
aomaker/maker/templates/apis.j2
aomaker/maker/templates/init.j2
aomaker/maker/templates/models.j2
aomaker/mock/__init__.py
aomaker/mock/mock_datas.py
aomaker/mock/mock_models.py
aomaker/mock/mock_server.py
aomaker/runner/__init__.py
aomaker/runner/args.py
aomaker/runner/base.py
aomaker/runner/context.py
aomaker/runner/models.py
aomaker/runner/parallel.py
aomaker/runner/progress.py
aomaker/runner/reporting.py
aomaker/send_msg/__init__.py
aomaker/send_msg/wechat.py
aomaker/utils/__init__.py
aomaker/utils/gen_allure_report.py
aomaker/utils/utils.py
aomaker-3.0.3.dist-info/licenses/LICENSE
aomaker-3.0.3.dist-info/METADATA
aomaker-3.0.3.dist-info/WHEEL
aomaker-3.0.3.dist-info/entry_points.txt
aomaker-3.0.3.dist-info/top_level.txt
aomaker-3.0.3.dist-info/RECORD
