Metadata-Version: 2.4
Name: aomaker
Version: 3.0.3
Summary: An api testing framework
Home-page: https://github.com/ae86sen/aomaker
Author: ancientone
Author-email: ancientone <listeningsss@163.com>
License: MIT License
Project-URL: Homepage, https://aomaker.cn
Project-URL: Repository, https://github.com/ae86sen/aomaker
Classifier: Programming Language :: Python :: 3
Classifier: License :: OSI Approved :: MIT License
Classifier: Operating System :: OS Independent
Classifier: Programming Language :: Python :: 3.11
Requires-Python: >=3.8
License-File: LICENSE
Requires-Dist: black==23.11.0
Requires-Dist: Jinja2==3.1.5
Requires-Dist: jsonpath==0.82
Requires-Dist: loguru==0.6.0
Requires-Dist: PyMySQL
Requires-Dist: pytest==7.2.0
Requires-Dist: PyYAML==6.0.2
Requires-Dist: requests==2.28.1
Requires-Dist: allure-pytest==2.8.24
Requires-Dist: pydantic==2.10.5
Requires-Dist: colorlog==6.7.0
Requires-Dist: jsonschema==4.17.3
Requires-Dist: genson==1.2.2
Requires-Dist: click==8.1.3
Requires-Dist: emoji==2.2.0
Requires-Dist: click-help-colors==0.9.1
Requires-Dist: tenacity==8.2.3
Requires-Dist: ruamel.yaml==0.17.21
Requires-Dist: jsonschema-extractor==2.0.2
Requires-Dist: rich==12.6.0
Requires-Dist: attrs==25.1.0
Requires-Dist: cattrs==24.1.2
Requires-Dist: fastapi==0.110.0
Requires-Dist: uvicorn==0.28.0
Requires-Dist: wsproto==1.2.0
Requires-Dist: inflection==0.5.1
Requires-Dist: PyJWT==2.10.1
Requires-Dist: python-multipart==0.0.20
Requires-Dist: apischema==0.19.0
Requires-Dist: deepdiff==8.6.0
Dynamic: author
Dynamic: home-page
Dynamic: license-file
